pysparq/__init__.py
pysparq/_core.cpython-39-x86_64-linux-gnu.so
pysparq/_core.pyi
pysparq.libs/libgomp-a34b3233.so.1.0.0
pysparq-0.0.3.dist-info/METADATA
pysparq-0.0.3.dist-info/WHEEL
pysparq-0.0.3.dist-info/RECORD
