Metadata-Version: 2.1
Name: pysparq
Version: 0.0.3
Summary: A sparse state quantum circuit simulator
Author-Email: Agony <chenzhaoyun@iai.ustc.edu.cn>
License: Apache-2.0
Requires-Python: >=3.9
Requires-Dist: numpy
Requires-Dist: pybind11_stubgen
